flask_stache.py
setup.py
Flask_Stache.egg-info/PKG-INFO
Flask_Stache.egg-info/SOURCES.txt
Flask_Stache.egg-info/dependency_links.txt
Flask_Stache.egg-info/not-zip-safe
Flask_Stache.egg-info/requires.txt
Flask_Stache.egg-info/top_level.txt